README.md
setup.py
src/azure_storage_utils/__init__.py
src/azure_storage_utils/pipelineoperator.py
src/azure_storage_utils.egg-info/PKG-INFO
src/azure_storage_utils.egg-info/SOURCES.txt
src/azure_storage_utils.egg-info/dependency_links.txt
src/azure_storage_utils.egg-info/requires.txt
src/azure_storage_utils.egg-info/top_level.txt
src/azure_storage_utils/auth/__init__.py
src/azure_storage_utils/auth/connectionstringutil.py
src/azure_storage_utils/mapping/__init__.py
src/azure_storage_utils/mapping/containermap.py
src/azure_storage_utils/mapping/filesharemap.py
src/azure_storage_utils/mapping/mapcomparator.py
src/azure_storage_utils/mapping/mapreporter.py