Metadata-Version: 1.1
Name: azure-storage-utils
Version: 1.0.29
Summary: A utility for tracking volume in and out of azure storage containers
Home-page: https://msazure.visualstudio.com/One/_git/RepoDepot
Author: Matthew Warren
Author-email: mawarren@microsoft.com
License: MIT
Keywords: maps flat blob storage accounts as if hierchical and compares changes between different mappings
Platform: UNKNOWN
Classifier: Development Status :: 4 - Beta
Classifier: Intended Audience :: Developers
Classifier: Topic :: Software Development :: Quality Assurance
Classifier: License :: OSI Approved :: MIT License
Classifier: Programming Language :: Python
Classifier: Programming Language :: Python :: 2.7
Classifier: Programming Language :: Python :: 3.8
